{
  "gitSyncId": "6758298efcecca327d786787_25d3c3dd-9916-4de2-9d3f-647f8f6ce181",
  "id": "Yangiliklar_InsertQuery",
  "pluginId": "postgres-plugin",
  "pluginType": "DB",
  "unpublishedAction": {
    "actionConfiguration": {
      "body": "INSERT INTO public.\"news\" (\n\t\"name\",\n\t\"desc\",\n\t\"image\",\n\t\"author_id\",\n\t\"created_at\",\n\t\"updated_at\",\n\t\"deleted_at\",\n\t\"created_by\",\n\t\"updated_by\",\n\t\"deleted_by\",\n\t\"name_ru\"\n)\nVALUES (\n\t'{{insert_form.formData.name}}',\n\t'{{insert_form.formData.desc}}',\n\t'{{insert_form.formData.image}}',\n\t'{{insert_form.formData.author_id}}',\n\t'{{insert_form.formData.created_at}}',\n\t'{{insert_form.formData.updated_at}}',\n\t'{{insert_form.formData.deleted_at}}',\n\t'{{insert_form.formData.created_by}}',\n\t'{{insert_form.formData.updated_by}}',\n\t'{{insert_form.formData.deleted_by}}',\n\t'{{insert_form.formData.name_ru}}'\n);",
      "encodeParamsToggle": true,
      "paginationType": "NONE",
      "pluginSpecifiedTemplates": [
        {
          "value": true
        }
      ],
      "timeoutInMillisecond": 10000
    },
    "confirmBeforeExecute": false,
    "datasource": {
      "id": "proliga",
      "isAutoGenerated": false,
      "name": "proliga",
      "pluginId": "postgres-plugin"
    },
    "executeOnLoad": false,
    "name": "InsertQuery",
    "pageId": "Yangiliklar",
    "userSetOnLoad": false
  }
}