{
  "gitSyncId": "676664725090fe25a81bf10e_2ca88438-ec7a-4c17-9059-5ba577cebc43",
  "id": "Turlar_create_tour",
  "pluginId": "postgres-plugin",
  "pluginType": "DB",
  "unpublishedAction": {
    "actionConfiguration": {
      "body": "SELECT create__tour__by__start_date__interval__count__comp_id({{DatePicker1.selectedDate}},4320,4320,{{Input1.text}},{{Select4.selectedOptionValue}})",
      "encodeParamsToggle": true,
      "paginationType": "NONE",
      "pluginSpecifiedTemplates": [
        {
          "value": true
        }
      ],
      "timeoutInMillisecond": 10000
    },
    "confirmBeforeExecute": false,
    "datasource": {
      "id": "proliga",
      "isAutoGenerated": false,
      "name": "proliga",
      "pluginId": "postgres-plugin"
    },
    "dynamicBindingPathList": [
      {
        "key": "body"
      }
    ],
    "executeOnLoad": false,
    "name": "create_tour",
    "pageId": "Turlar",
    "userSetOnLoad": false
  }
}