{
  "accentColor": "{{appsmith.theme.colors.primaryColor}}",
  "animateLoading": true,
  "borderRadius": "{{appsmith.theme.borderRadius.appBorderRadius}}",
  "bottomRow": 24,
  "boxShadow": "none",
  "defaultOptionValue": "",
  "dynamicBindingPathList": [
    {
      "key": "accentColor"
    },
    {
      "key": "borderRadius"
    },
    {
      "key": "sourceData"
    }
  ],
  "dynamicHeight": "FIXED",
  "dynamicPropertyPathList": [
    {
      "key": "sourceData"
    }
  ],
  "dynamicTriggerPathList": [],
  "isDisabled": false,
  "isFilterable": true,
  "isLoading": false,
  "isRequired": false,
  "isVisible": true,
  "key": "lhd6lo6nnl",
  "labelAlignment": "left",
  "labelPosition": "Top",
  "labelText": "Klub",
  "labelTextSize": "0.875rem",
  "labelWidth": 5,
  "leftColumn": 19,
  "maxDynamicHeight": 9000,
  "minDynamicHeight": 4,
  "minWidth": 450,
  "mobileBottomRow": 8,
  "mobileLeftColumn": 1,
  "mobileRightColumn": 21,
  "mobileTopRow": 1,
  "needsErrorInfo": false,
  "optionLabel": "label",
  "optionValue": "value",
  "parentColumnSpace": 20.21875,
  "parentId": "0",
  "parentRowSpace": 10,
  "placeholderText": "Klub",
  "renderMode": "CANVAS",
  "responsiveBehavior": "fill",
  "rightColumn": 37,
  "serverSideFiltering": false,
  "sourceData": "{{ \n  get_club.data\n    .filter(row => !Select1.selectedOptionValue || row.competition_id === Select1.selectedOptionValue)\n    .map(row => ({ label: row.name, value: row.id }))\n}}",
  "topRow": 17,
  "type": "SELECT_WIDGET",
  "version": 1,
  "widgetId": "dp64h0czh7",
  "widgetName": "Select2"
}